django_request_cache/__init__.py
django_request_cache/middleware.py
django_request_cache-1.5.0.dist-info/LICENSE
django_request_cache-1.5.0.dist-info/METADATA
django_request_cache-1.5.0.dist-info/WHEEL
django_request_cache-1.5.0.dist-info/top_level.txt
django_request_cache-1.5.0.dist-info/RECORD
